geo_measurements/__init__.py
geo_measurements/geo_measurements.py
geo_measurements/geo_data/ne_10m_admin_0_countries.README.html
geo_measurements/geo_data/ne_10m_admin_0_countries.VERSION.txt
geo_measurements/geo_data/ne_10m_admin_0_countries.cpg
geo_measurements/geo_data/ne_10m_admin_0_countries.dbf
geo_measurements/geo_data/ne_10m_admin_0_countries.prj
geo_measurements/geo_data/ne_10m_admin_0_countries.shp
geo_measurements/geo_data/ne_10m_admin_0_countries.shx
geo_measurements/geo_data/world-continents.dbf
geo_measurements/geo_data/world-continents.prj
geo_measurements/geo_data/world-continents.sbx
geo_measurements/geo_data/world-continents.shp
geo_measurements/geo_data/world-continents.shp.xml
geo_measurements/geo_data/world-continents.shx
geo_measurements-0.0.2.dist-info/LICENSE.txt
geo_measurements-0.0.2.dist-info/METADATA
geo_measurements-0.0.2.dist-info/WHEEL
geo_measurements-0.0.2.dist-info/top_level.txt
geo_measurements-0.0.2.dist-info/RECORD
