Metadata-Version: 2.1
Name: geo_measurements
Version: 0.0.2
Summary: A suite of geospatial utility functions for precise geographic coordinate measurements.
Home-page: https://github.com/b3n3c/geo_measurements
Author: b3n3c
License-File: LICENSE.txt
Requires-Dist: utm>=0.7.0
Requires-Dist: geographiclib>=2.0
Requires-Dist: shapely>=2.0
Requires-Dist: pyproj>=3.7.0
Requires-Dist: geopandas>=1.0.0
